bookshelf/__init__.py
bookshelf/__main__.py
bookshelf/console.py
bookshelf/exceptions.py
bookshelf/models.py
bookshelf/param_types.py
bookshelf/storage.py
test/__init__.py
test/test_exceptions.py
test/test_models.py
test/test_param_types.py
test/test_storage.py
test/utils/__init__.py
test/utils/chapter_utils.py
test/utils/storage_utils.py
bookshelf_cli-0.4.0.dist-info/LICENSE
bookshelf_cli-0.4.0.dist-info/METADATA
bookshelf_cli-0.4.0.dist-info/WHEEL
bookshelf_cli-0.4.0.dist-info/entry_points.txt
bookshelf_cli-0.4.0.dist-info/top_level.txt
bookshelf_cli-0.4.0.dist-info/RECORD
