Metadata-Version: 2.1
Name: bookshelf-cli
Version: 0.4.0
Summary: 📚 A CLI tool for tracking your stories in the SDLC.
Home-page: https://bookshelf.docs.joss.dev/
Author: Joss Moffatt
Project-URL: Issue Tracker, https://github.com/jossmoff/bookshelf/issues
Requires-Python: >=3.10
License-File: LICENSE
Requires-Dist: rich >=13.6.0
Requires-Dist: rich-click >=1.7.0
